npex/alignment.py
npex/blob.py
npex/datachunk.py
npex/gui.py
npex/npex.py
npex/peaks.py
npex/tiffreader.py
npex-0.0.1.dist-info/LICENSE
npex-0.0.1.dist-info/METADATA
npex-0.0.1.dist-info/WHEEL
npex-0.0.1.dist-info/top_level.txt
npex-0.0.1.dist-info/RECORD
